{
	"schemaVersion": 1,
	"id": "livestock_husbandry",
	"version": "${version}",
	"name": "LiveStock & Husbandry",
	"description": "A vanilla-style livestock mod adding chicken nests, animal troughs, and better farm animal behavior.!",
	"authors": [
		"GameMech007!"
	],
	"contact": {
		"homepage": "https://modrinth.com/mod/LiveStock-Husbandry",
		"sources": "https://github.com/GameMech007-git/LiveStock-Husbandry",
		"issues": "https://github.com/GameMech007-git/LiveStock-Husbandry/issues"
	},
	"license": "GPL 3.0",
	"icon": "assets/livestock_husbandry/icon.png",
	"environment": "*",
	"entrypoints": {
		"main": [
			"com.livestockhusbandry.LiveStockHusbandry"
		],
		"client": [
			"com.livestockhusbandry.client.LiveStockHusbandryClient"
		]
	},
	"mixins": [
		"livestock_husbandry.mixins.json",
		{
			"config": "livestock_husbandry.client.mixins.json",
			"environment": "client"
		}
	],
	"depends": {
		"fabricloader": ">=0.19.3",
		"minecraft": "~26.1.2",
		"java": ">=25",
		"fabric-api": "*"
	}
}